hatzakislab/__init__.py
hatzakislab/conventional_model.py
hatzakislab/inference_drop.py
hatzakislab/main.py
hatzakislab-0.1.1.dist-info/METADATA
hatzakislab-0.1.1.dist-info/WHEEL
hatzakislab-0.1.1.dist-info/top_level.txt
hatzakislab-0.1.1.dist-info/RECORD
