Metadata-Version: 2.2
Name: hatzakislab
Version: 0.1.1
Requires-Dist: pandas
Requires-Dist: numpy
Requires-Dist: matplotlib
Requires-Dist: scipy
Dynamic: requires-dist
